wcatapi/__init__.py
wcatapi-1.0.4.dist-info/LICENSE
wcatapi-1.0.4.dist-info/METADATA
wcatapi-1.0.4.dist-info/WHEEL
wcatapi-1.0.4.dist-info/top_level.txt
wcatapi-1.0.4.dist-info/RECORD
