Metadata-Version: 2.1
Name: wcatapi
Version: 1.0.4
Summary: CatApi
Home-page: https://api.wispace.ru/cat
Author: WiSpace
Author-email: wiforumit@gmail.com
License: UNKNOWN
Platform: UNKNOWN
Classifier: Programming Language :: Python :: 3.10
Requires-Python: >=3.6
License-File: LICENSE
